{
    "page":"events_schedule",
    "testDefinitions":[
        {"name":"Verify Events Title","objectType":"verify_value","by":"class","objectId":"events-schedule-title"},
        {"name":"Verify Prime Grid","objectType":"verify_value","by":"class","objectId":"primeTimeGridToday"},
        {"name":"Verify Prime Tile","objectType":"verify_value","by":"class","objectId":"primeTimeGridTile"},
        {"name":"Verify Prime Time","objectType":"verify_value","by":"class","objectId":"primeTimeGridTime"},
        {"name":"Verify TV Schedule","objectType":"verify_value","by":"class","objectId":"tv-schedule-link"}
        ]
}
