{
	"page":"Favorites",
	"testDefinitions":[
		{"name":"Click Add New Favorites Button","objectType":"click","by":"xpath","objectId":"//button[contains(@class,'add-favorites-link')]"},
		{"name":"Click Close Gnatout Button","objectType":"click","by":"xpath","objectId":"//div[contains(@class,'gnatout')]//button[@class='image-button close']"},
		{"name":"Click Done on Favorites","objectType":"click","by":"xpath","objectId":"//div[contains(@class,'manage-btn')][button[contains(.,'DONE')]]"},
		{"name":"Click Manage on Favorites","objectType":"click","by":"xpath","objectId":"//div[contains(@class,'manage-btn')][button[contains(.,'MANAGE')]]"},
		{"name":"Click Remove on Favorite","objectType":"click","by":"xpath","objectId":"//button[contains(@class,'favorite-remove-button')]"},
		{"name":"Hover Manage on Favorites","objectType":"hover","by":"xpath","objectId":"//div[@class='favorites-menu']"},
		{"name":"Randomize Favorite NCAA Conference","objectType":"script","by":"xpath","objectId":"Favorites"},
		{"name":"Randomize Favorite NCAA League","objectType":"script","by":"xpath","objectId":"Favorites"},
		{"name":"Randomize Favorite NCAA Player","objectType":"script","by":"xpath","objectId":"Favorites"},
		{"name":"Randomize Favorite NCAA Team","objectType":"script","by":"xpath","objectId":"Favorites"},
		{"name":"Randomize Favorite Pro League","objectType":"script","by":"xpath","objectId":"Favorites"},
		{"name":"Randomize Favorite Pro Player","objectType":"script","by":"xpath","objectId":"Favorites"},
		{"name":"Randomize Favorite Pro Team","objectType":"script","by":"xpath","objectId":"Favorites"},
		{"name":"Randomize Favorite Show","objectType":"script","by":"xpath","objectId":"Favorites"},
		{"name":"Verify Favorites Nav Text","objectType":"verify_value","by":"xpath","objectId":"//*[contains(@class,'add-your-favorites') or contains(@class,'base-state')]"},
		{"name":"Verify Gnatout is Displayed","objectType":"verify_displayed","by":"xpath","objectId":"//div[contains(@class,'gnatout')]"},
		{"name":"Verify Number of Favorites","objectType":"verify_count","by":"xpath","objectId":"//div[@class='favorites-menu-items']//a"}

	]
}