{
	"page":"MLB_Scores",
	"testDefinitions":[
		{"name":"Scroll Back One Day","objectType":"script","by":"xpath","objectId":"MLB_Scores"},		
		{"name":"Scroll Forward One Day","objectType":"script","by":"xpath","objectId":"MLB_Scores"},		
		{"name":"Select Regular Season MLB Date","objectType":"script","by":"xpath","objectId":"MLB_Scores"},
		{"name":"Verify MLB Date","objectType":"script","by":"xpath","objectId":"MLB_Scores"},
		{"name":"Verify Event","objectType":"script","by":"xpath","objectId":"DailyTeam_Scores"},
		{"name":"Verify Events in Segment","objectType":"script","by":"xpath","objectId":"DailyTeam_Scores"}
	]
}